{
  "parent": "minecraft:recipes/root",
  "rewards": {
    "recipes": [
      "minecraft:powered_rail"
    ]
  },
  "criteria": {
    "has_the_recipe": {
      "trigger": "minecraft:recipe_unlocked",
      "conditions": {
        "recipe": "minecraft:powered_rail"
      }
    },
    "gained_engineering": {
      "trigger": "commerce:gained_competencies",
      "conditions": {
        "competencies": [
          "engineering"
        ]
      }
    }
  },
  "requirements": [
    [
      "has_the_recipe",
      "gained_engineering"
    ]
  ]
}